{
    "raw": "sha1://a72275321699f745f7588877b02a468140597aaa/raw.mda?manifest=859ea5e1716afb2a5eb43f0adafe7bae19b2c277",
    "params": {
        "samplerate": 30000.0,
        "spike_sign": -1
    },
    "geom": [
        [
            0.0,
            0.0
        ],
        [
            0.0,
            1.0
        ],
        [
            0.0,
            2.0
        ],
        [
            0.0,
            3.0
        ]
    ],
    "self_reference": "sha1://f77b17673e2e8cf71b7c1c845cb4b5cf0875df09/010_synth.json"
}