{
    "raw": "sha1://0f8ec89c54e9caffbc6c6fea6944966d6e0c78f4/raw.mda?manifest=30f0786b9121899e3f8928b5c4ca0bd735698a66",
    "params": {
        "spike_sign": -1,
        "samplerate": 32000,
        "scale_factor": 0.0001
    },
    "geom": [
        [
            -11.0,
            308.0
        ],
        [
            11.0,
            308.0
        ],
        [
            -11.0,
            286.0
        ],
        [
            11.0,
            286.0
        ],
        [
            -11.0,
            264.0
        ],
        [
            11.0,
            264.0
        ],
        [
            -11.0,
            242.0
        ],
        [
            11.0,
            242.0
        ],
        [
            -11.0,
            220.0
        ],
        [
            11.0,
            220.0
        ],
        [
            -11.0,
            198.0
        ],
        [
            11.0,
            198.0
        ],
        [
            -11.0,
            176.0
        ],
        [
            11.0,
            176.0
        ],
        [
            -11.0,
            154.0
        ],
        [
            11.0,
            154.0
        ],
        [
            -11.0,
            132.0
        ],
        [
            11.0,
            132.0
        ],
        [
            -11.0,
            110.0
        ],
        [
            11.0,
            110.0
        ],
        [
            -11.0,
            88.0
        ],
        [
            11.0,
            88.0
        ],
        [
            -11.0,
            66.0
        ],
        [
            11.0,
            66.0
        ],
        [
            -11.0,
            44.0
        ],
        [
            11.0,
            44.0
        ],
        [
            -11.0,
            22.0
        ],
        [
            11.0,
            22.0
        ],
        [
            -11.0,
            0.0
        ],
        [
            11.0,
            0.0
        ]
    ],
    "self_reference": "sha1://8990d253b73a1671ca59f1ed7f09de99397975c4/set6.json"
}