{
    "raw": "sha1://485868b01078dd7ab223d38c446bae4ee7f92496/raw.mda?manifest=171580e0db8d3cd4745609e43af5a9be51eeebdf",
    "params": {
        "spike_sign": -1,
        "samplerate": 30000
    },
    "geom": [
        [
            11.0,
            60.0
        ],
        [
            59.0,
            80.0
        ],
        [
            27.0,
            80.0
        ],
        [
            43.0,
            100.0
        ],
        [
            11.0,
            100.0
        ],
        [
            59.0,
            120.0
        ],
        [
            27.0,
            120.0
        ],
        [
            43.0,
            140.0
        ],
        [
            11.0,
            140.0
        ],
        [
            59.0,
            160.0
        ],
        [
            27.0,
            160.0
        ],
        [
            43.0,
            180.0
        ],
        [
            11.0,
            180.0
        ],
        [
            59.0,
            200.0
        ],
        [
            27.0,
            200.0
        ],
        [
            43.0,
            220.0
        ]
    ],
    "self_reference": "sha1://514eaa91186e96f041086459c18bc314aba7bc8f/002_synth.json"
}