{
    "raw": "sha1://d15c1ccc75d91cfdad733a1fe13db1aed34b1a76/raw.mda?manifest=8887a53ea24df90548e3281f8499a28bc0f10904",
    "params": {
        "samplerate": 20000,
        "spike_sign": -1,
        "scale_factor": 0.1
    },
    "geom": [
        [
            0.0,
            0.0
        ],
        [
            32.0,
            0.0
        ],
        [
            0.0,
            20.0
        ],
        [
            32.0,
            20.0
        ],
        [
            0.0,
            40.0
        ],
        [
            32.0,
            40.0
        ],
        [
            0.0,
            60.0
        ],
        [
            32.0,
            60.0
        ],
        [
            0.0,
            80.0
        ],
        [
            32.0,
            80.0
        ],
        [
            0.0,
            100.0
        ],
        [
            32.0,
            100.0
        ],
        [
            0.0,
            120.0
        ],
        [
            32.0,
            120.0
        ],
        [
            0.0,
            140.0
        ],
        [
            32.0,
            140.0
        ],
        [
            0.0,
            160.0
        ],
        [
            32.0,
            160.0
        ],
        [
            0.0,
            180.0
        ],
        [
            32.0,
            180.0
        ],
        [
            0.0,
            200.0
        ],
        [
            32.0,
            200.0
        ],
        [
            0.0,
            220.0
        ],
        [
            32.0,
            220.0
        ],
        [
            0.0,
            240.0
        ],
        [
            32.0,
            240.0
        ],
        [
            0.0,
            260.0
        ],
        [
            32.0,
            260.0
        ],
        [
            0.0,
            280.0
        ],
        [
            32.0,
            280.0
        ],
        [
            0.0,
            300.0
        ],
        [
            32.0,
            300.0
        ],
        [
            0.0,
            320.0
        ],
        [
            32.0,
            320.0
        ],
        [
            0.0,
            340.0
        ],
        [
            32.0,
            340.0
        ],
        [
            0.0,
            360.0
        ],
        [
            32.0,
            360.0
        ],
        [
            0.0,
            380.0
        ],
        [
            32.0,
            380.0
        ],
        [
            0.0,
            400.0
        ],
        [
            32.0,
            400.0
        ],
        [
            0.0,
            420.0
        ],
        [
            32.0,
            420.0
        ],
        [
            0.0,
            440.0
        ],
        [
            32.0,
            440.0
        ],
        [
            0.0,
            460.0
        ],
        [
            32.0,
            460.0
        ],
        [
            0.0,
            480.0
        ],
        [
            32.0,
            480.0
        ],
        [
            0.0,
            500.0
        ],
        [
            32.0,
            500.0
        ],
        [
            0.0,
            520.0
        ],
        [
            32.0,
            520.0
        ],
        [
            0.0,
            540.0
        ],
        [
            32.0,
            540.0
        ],
        [
            0.0,
            560.0
        ],
        [
            32.0,
            560.0
        ],
        [
            0.0,
            580.0
        ],
        [
            32.0,
            580.0
        ]
    ],
    "self_reference": "sha1://fbf64ade9975e73f302fbf5b139dc2eacf303ecb/static_8x_B_2A.json"
}