{
    "raw": "sha1://4e601e6c0e2f2ed764d28424532017c36e3d6e92/raw.mda?manifest=2fd01aad9609a30545ca36c7f2e9be7b95a89f03",
    "params": {
        "samplerate": 30000,
        "spike_sign": -1
    },
    "geom": [
        [
            1.0,
            0.0
        ],
        [
            2.0,
            0.0
        ],
        [
            3.0,
            0.0
        ],
        [
            4.0,
            0.0
        ]
    ],
    "self_reference": "sha1://32ce371899ddf6a8a8c11f5198a35fc6faf36712/008_synth.json"
}