{
    "raw": "sha1://94f28324b6eba2a90f00ae9d0e09d29d3b4c71b1/raw.mda?manifest=40e1bd2aab739330d159cd4b7fd2443ee2660d7f",
    "params": {
        "spike_sign": -1,
        "samplerate": 30000,
        "scale_factor": 0.195
    },
    "geom": [
        [
            34.5,
            154.0
        ],
        [
            11.5,
            165.0
        ],
        [
            23.0,
            165.0
        ],
        [
            34.5,
            165.0
        ],
        [
            0.0,
            176.0
        ],
        [
            11.5,
            176.0
        ],
        [
            23.0,
            176.0
        ],
        [
            34.5,
            176.0
        ],
        [
            0.0,
            187.0
        ],
        [
            11.5,
            187.0
        ],
        [
            34.5,
            187.0
        ],
        [
            0.0,
            198.0
        ],
        [
            11.5,
            198.0
        ],
        [
            34.5,
            198.0
        ],
        [
            0.0,
            209.0
        ],
        [
            11.5,
            209.0
        ],
        [
            23.0,
            209.0
        ],
        [
            34.5,
            209.0
        ],
        [
            0.0,
            220.0
        ],
        [
            11.5,
            220.0
        ],
        [
            0.0,
            231.0
        ],
        [
            11.5,
            231.0
        ],
        [
            23.0,
            231.0
        ],
        [
            34.5,
            231.0
        ],
        [
            0.0,
            242.0
        ],
        [
            11.5,
            242.0
        ],
        [
            23.0,
            242.0
        ],
        [
            34.5,
            242.0
        ],
        [
            11.5,
            253.0
        ],
        [
            23.0,
            253.0
        ],
        [
            34.5,
            253.0
        ],
        [
            34.5,
            264.0
        ]
    ],
    "self_reference": "sha1://26be7705a2ed4b43bd37b12868f9adcc7fc7bc74/624_5_2.json"
}