{
    "raw": "sha1://50e66a016843ab50cc90b24c2d7d8f84f2545a33/raw.mda?manifest=41b38041f248ffacb073cdbb013e12f84d27eed9",
    "params": {
        "spike_sign": -1,
        "samplerate": 20000,
        "scale_factor": 0.305176
    },
    "geom": [
        [
            0.0,
            0.0
        ],
        [
            0.0,
            25.0
        ],
        [
            0.0,
            50.0
        ],
        [
            0.0,
            75.0
        ],
        [
            0.0,
            100.0
        ]
    ],
    "self_reference": "sha1://7e68e39d8039585bae7b1f20a256b06489e5c03b/d13522_d1352211.json"
}