{
    "raw": "sha1://89953bd25ebe6520acd3c6f11536f2c142c2a5af/raw.mda?manifest=9b0ac427d15d2e68ed4fe5ba8e840476d1da9a2c",
    "params": {
        "spike_sign": -1,
        "samplerate": 10000,
        "scale_factor": 0.305176
    },
    "geom": [
        [
            0.0,
            0.0
        ],
        [
            0.0,
            25.0
        ],
        [
            0.0,
            50.0
        ],
        [
            0.0,
            75.0
        ],
        [
            0.0,
            100.0
        ]
    ],
    "self_reference": "sha1://54c5068d70f5b0f5aca08860ab374af7ba2e8752/d15121_d1512101.json"
}