{
    "raw": "sha1://24643544ea28619c47ca1f3612032de2d31a3af8/raw.mda?manifest=55324096eb049e7433c129644a8f16b21f6a8a5e",
    "params": {
        "spike_sign": -1,
        "samplerate": 20000,
        "scale_factor": 0.305176
    },
    "geom": [
        [
            0.0,
            0.0
        ],
        [
            0.0,
            25.0
        ],
        [
            0.0,
            50.0
        ],
        [
            0.0,
            75.0
        ],
        [
            0.0,
            100.0
        ],
        [
            0.0,
            125.0
        ],
        [
            0.0,
            150.0
        ],
        [
            0.0,
            175.0
        ],
        [
            0.0,
            200.0
        ],
        [
            0.0,
            225.0
        ],
        [
            0.0,
            250.0
        ],
        [
            0.0,
            275.0
        ]
    ],
    "self_reference": "sha1://1c9a7c1aa65827ee0e6015d964b6cc5320c7f417/d15712_d15712.001.json"
}