{
    "raw": "sha1://e26070121b904bf67db0ca60687104169ba7bb28/raw.mda?manifest=12508689ac76aa0c781945a6597eb0b982fc73c2",
    "params": {
        "samplerate": 30000.0,
        "spike_sign": -1
    },
    "geom": [
        [
            1.0,
            0.0
        ],
        [
            2.0,
            0.0
        ],
        [
            3.0,
            0.0
        ],
        [
            4.0,
            0.0
        ],
        [
            5.0,
            0.0
        ],
        [
            6.0,
            0.0
        ],
        [
            7.0,
            0.0
        ],
        [
            8.0,
            0.0
        ]
    ],
    "self_reference": "sha1://1a68afada5d21f5cfa517281d64511a18ecd218e/007_synth.json"
}