{
    "name": "SYNTH_MAGLAND",
    "info": {
        "label": "SYNTH_MAGLAND",
        "electrode_type": [
            "tetrode",
            "silicon-probe"
        ],
        "doi": null,
        "ground_truth": "simulation",
        "recording_type": "in-silico",
        "organism": null
    },
    "description": "# SYNTH_MAGLAND\n\n## Synthetic groundtruth generated by spikeforest\n- Data generated by James Jun on Oct 19, 2018 based on Jeremy Magland's code\n- Waveform templates are generated using parameteric curves\n- Spike timing was randomly generated from the Poisson distribution and white noise is added\n- [Code is available on Github](https://github.com/magland/spikeforest/tree/master/working/gen_synth_datasets/8trode) (TODO: need to update this link)\n  - run `python working/gen_synth_datasets/8trode/driver.py`\n  - commit#: eaf42d7a76dfd31b4150b752815d8efffdc51908\n- Required packages\n  - [spikeinterface](https://github.com/colehurwitz31/spikeinterface)\n  - [mountainlab_pytools](https://github.com/magland/mountainlab_pytools)\n\n## Studies contained this dataset\n- Directory names follow a format `datasets_noise#_K#_C#` where\n- `noise#`: noise value added (SD of white noise, 10 or 20)\n- `K#`: number of units simulated (10 or 20)\n- `C#`: number of electrodes (4 or 8 channels)",
    "studies": [
        {
            "name": "synth_magland_noise20_K20_C8",
            "studySetName": "SYNTH_MAGLAND",
            "recordings": [
                {
                    "name": "001_synth",
                    "studyName": "synth_magland_noise20_K20_C8",
                    "studySetName": "SYNTH_MAGLAND",
                    "sampleRateHz": 30000.0,
                    "numChannels": 8,
                    "durationSec": 600.0,
                    "numTrueUnits": 20,
                    "spikeSign": -1,
                    "recordingUri": "sha1://30fa2691def609ef390c939e0a8f77f54278b3eb/001_synth.json",
                    "sortingTrueUri": "sha1://b00b8ac950630c848b78b36cf0fbc1533cd63faa/001_synth.firings_true.json"
                },
                {
                    "name": "002_synth",
                    "studyName": "synth_magland_noise20_K20_C8",
                    "studySetName": "SYNTH_MAGLAND",
                    "sampleRateHz": 30000.0,
                    "numChannels": 8,
                    "durationSec": 600.0,
                    "numTrueUnits": 20,
                    "spikeSign": -1,
                    "recordingUri": "sha1://1393a1797d593ae76de355caff089c53adb92703/002_synth.json",
                    "sortingTrueUri": "sha1://54160fdda6a31902a8273a65e92c41bca3ad0807/002_synth.firings_true.json"
                },
                {
                    "name": "003_synth",
                    "studyName": "synth_magland_noise20_K20_C8",
                    "studySetName": "SYNTH_MAGLAND",
                    "sampleRateHz": 30000.0,
                    "numChannels": 8,
                    "durationSec": 600.0,
                    "numTrueUnits": 20,
                    "spikeSign": -1,
                    "recordingUri": "sha1://7486b352f2ff28a8a9b9f5ec94ecbf43a22ecc79/003_synth.json",
                    "sortingTrueUri": "sha1://a15b1ad1f7fe6a5e7fd4918cdc3f7b51a45786c8/003_synth.firings_true.json"
                },
                {
                    "name": "004_synth",
                    "studyName": "synth_magland_noise20_K20_C8",
                    "studySetName": "SYNTH_MAGLAND",
                    "sampleRateHz": 30000.0,
                    "numChannels": 8,
                    "durationSec": 600.0,
                    "numTrueUnits": 20,
                    "spikeSign": -1,
                    "recordingUri": "sha1://20aeead62e3597f0fa0d21205baedf6f625a71c8/004_synth.json",
                    "sortingTrueUri": "sha1://eb7e5231fb0083f1ee814f40677c8a71e874036c/004_synth.firings_true.json"
                },
                {
                    "name": "005_synth",
                    "studyName": "synth_magland_noise20_K20_C8",
                    "studySetName": "SYNTH_MAGLAND",
                    "sampleRateHz": 30000.0,
                    "numChannels": 8,
                    "durationSec": 600.0,
                    "numTrueUnits": 20,
                    "spikeSign": -1,
                    "recordingUri": "sha1://4a17c3e32ed90a2356bca53da2bf5f9368eaeaf1/005_synth.json",
                    "sortingTrueUri": "sha1://ef1640a021e9935daf18b32cd6f459ba810ede83/005_synth.firings_true.json"
                },
                {
                    "name": "006_synth",
                    "studyName": "synth_magland_noise20_K20_C8",
                    "studySetName": "SYNTH_MAGLAND",
                    "sampleRateHz": 30000.0,
                    "numChannels": 8,
                    "durationSec": 600.0,
                    "numTrueUnits": 20,
                    "spikeSign": -1,
                    "recordingUri": "sha1://576b56ccd36a3f92d03b562050e306c199aa310b/006_synth.json",
                    "sortingTrueUri": "sha1://0a1e7eb59eabac5a4a111f0ac329e1c8bd48f913/006_synth.firings_true.json"
                },
                {
                    "name": "007_synth",
                    "studyName": "synth_magland_noise20_K20_C8",
                    "studySetName": "SYNTH_MAGLAND",
                    "sampleRateHz": 30000.0,
                    "numChannels": 8,
                    "durationSec": 600.0,
                    "numTrueUnits": 20,
                    "spikeSign": -1,
                    "recordingUri": "sha1://1a68afada5d21f5cfa517281d64511a18ecd218e/007_synth.json",
                    "sortingTrueUri": "sha1://c43bce539166cc229a565608d1ab5c07e4e1355d/007_synth.firings_true.json"
                },
                {
                    "name": "008_synth",
                    "studyName": "synth_magland_noise20_K20_C8",
                    "studySetName": "SYNTH_MAGLAND",
                    "sampleRateHz": 30000.0,
                    "numChannels": 8,
                    "durationSec": 600.0,
                    "numTrueUnits": 20,
                    "spikeSign": -1,
                    "recordingUri": "sha1://912d34bc03734ff3c5fda2d1a0a12502fa42820c/008_synth.json",
                    "sortingTrueUri": "sha1://f46a6833aa07c773a11a0c478d6219d2360bd865/008_synth.firings_true.json"
                },
                {
                    "name": "009_synth",
                    "studyName": "synth_magland_noise20_K20_C8",
                    "studySetName": "SYNTH_MAGLAND",
                    "sampleRateHz": 30000.0,
                    "numChannels": 8,
                    "durationSec": 600.0,
                    "numTrueUnits": 20,
                    "spikeSign": -1,
                    "recordingUri": "sha1://51ea204c1f8cf644afff52b75e04109e60980c02/009_synth.json",
                    "sortingTrueUri": "sha1://b32f6ac11757dc8ed423357e7dd5cbb126970b5b/009_synth.firings_true.json"
                },
                {
                    "name": "010_synth",
                    "studyName": "synth_magland_noise20_K20_C8",
                    "studySetName": "SYNTH_MAGLAND",
                    "sampleRateHz": 30000.0,
                    "numChannels": 8,
                    "durationSec": 600.0,
                    "numTrueUnits": 20,
                    "spikeSign": -1,
                    "recordingUri": "sha1://f4f6df20cfbc35d3073957ed23a4682ba8cd500f/010_synth.json",
                    "sortingTrueUri": "sha1://371e945aabb65271f4109600d316ee2fd9d064c6/010_synth.firings_true.json"
                }
            ],
            "self_reference": "sha1://f9c87fafee8c030bd622074538adfdea73b309a6/synth_magland_noise20_K20_C8.json"
        },
        {
            "name": "synth_magland_noise10_K10_C4",
            "studySetName": "SYNTH_MAGLAND",
            "recordings": [
                {
                    "name": "001_synth",
                    "studyName": "synth_magland_noise10_K10_C4",
                    "studySetName": "SYNTH_MAGLAND",
                    "sampleRateHz": 30000.0,
                    "numChannels": 4,
                    "durationSec": 600.0,
                    "numTrueUnits": 10,
                    "spikeSign": -1,
                    "recordingUri": "sha1://f060669aadaa0f8ebe296bf72895df3899f8cf45/001_synth.json",
                    "sortingTrueUri": "sha1://d26dfd7798286d0696d0707b8202631914b193d7/001_synth.firings_true.json"
                },
                {
                    "name": "002_synth",
                    "studyName": "synth_magland_noise10_K10_C4",
                    "studySetName": "SYNTH_MAGLAND",
                    "sampleRateHz": 30000.0,
                    "numChannels": 4,
                    "durationSec": 600.0,
                    "numTrueUnits": 10,
                    "spikeSign": -1,
                    "recordingUri": "sha1://94bbae431c1ae18bb1d3dbb2d295e833c15a24c8/002_synth.json",
                    "sortingTrueUri": "sha1://9190d5ee145f897dbb1c95c14e350690afcd93c9/002_synth.firings_true.json"
                },
                {
                    "name": "003_synth",
                    "studyName": "synth_magland_noise10_K10_C4",
                    "studySetName": "SYNTH_MAGLAND",
                    "sampleRateHz": 30000.0,
                    "numChannels": 4,
                    "durationSec": 600.0,
                    "numTrueUnits": 10,
                    "spikeSign": -1,
                    "recordingUri": "sha1://5cd49e408506bec769e910e548d4b1e90d89adce/003_synth.json",
                    "sortingTrueUri": "sha1://4af023c4d4b72610c0f9aca4f3e036c29f47a848/003_synth.firings_true.json"
                },
                {
                    "name": "004_synth",
                    "studyName": "synth_magland_noise10_K10_C4",
                    "studySetName": "SYNTH_MAGLAND",
                    "sampleRateHz": 30000.0,
                    "numChannels": 4,
                    "durationSec": 600.0,
                    "numTrueUnits": 10,
                    "spikeSign": -1,
                    "recordingUri": "sha1://4d7d4cdbdc0c9898de179099cd05d49483e661c5/004_synth.json",
                    "sortingTrueUri": "sha1://d3b04fe7c80dbe3a5cce2ca56a41ce8299bfc407/004_synth.firings_true.json"
                },
                {
                    "name": "005_synth",
                    "studyName": "synth_magland_noise10_K10_C4",
                    "studySetName": "SYNTH_MAGLAND",
                    "sampleRateHz": 30000.0,
                    "numChannels": 4,
                    "durationSec": 600.0,
                    "numTrueUnits": 10,
                    "spikeSign": -1,
                    "recordingUri": "sha1://e5a8d179cc72a393c1e1e385ca208fada6bc35fa/005_synth.json",
                    "sortingTrueUri": "sha1://273ad06b58318339ae60fd8117b39b882e74ac05/005_synth.firings_true.json"
                },
                {
                    "name": "006_synth",
                    "studyName": "synth_magland_noise10_K10_C4",
                    "studySetName": "SYNTH_MAGLAND",
                    "sampleRateHz": 30000.0,
                    "numChannels": 4,
                    "durationSec": 600.0,
                    "numTrueUnits": 10,
                    "spikeSign": -1,
                    "recordingUri": "sha1://6e03510d5c15a871d90408dd1de98090696ddd71/006_synth.json",
                    "sortingTrueUri": "sha1://17d8aa448caca72ec9846355fbe67c7d7269f435/006_synth.firings_true.json"
                },
                {
                    "name": "007_synth",
                    "studyName": "synth_magland_noise10_K10_C4",
                    "studySetName": "SYNTH_MAGLAND",
                    "sampleRateHz": 30000.0,
                    "numChannels": 4,
                    "durationSec": 600.0,
                    "numTrueUnits": 10,
                    "spikeSign": -1,
                    "recordingUri": "sha1://b2b5f55c32c9e56f21682a41ca7ff9c7e262bc00/007_synth.json",
                    "sortingTrueUri": "sha1://b978355b9d2dd67c69e17e320f853d6fd274c1bf/007_synth.firings_true.json"
                },
                {
                    "name": "008_synth",
                    "studyName": "synth_magland_noise10_K10_C4",
                    "studySetName": "SYNTH_MAGLAND",
                    "sampleRateHz": 30000.0,
                    "numChannels": 4,
                    "durationSec": 600.0,
                    "numTrueUnits": 10,
                    "spikeSign": -1,
                    "recordingUri": "sha1://32ce371899ddf6a8a8c11f5198a35fc6faf36712/008_synth.json",
                    "sortingTrueUri": "sha1://f49d8c8ee065da4a66f9ce3f4c30b25f9f512d24/008_synth.firings_true.json"
                },
                {
                    "name": "009_synth",
                    "studyName": "synth_magland_noise10_K10_C4",
                    "studySetName": "SYNTH_MAGLAND",
                    "sampleRateHz": 30000.0,
                    "numChannels": 4,
                    "durationSec": 600.0,
                    "numTrueUnits": 10,
                    "spikeSign": -1,
                    "recordingUri": "sha1://1d755e57fc8fb637285e47491fb327064d76c094/009_synth.json",
                    "sortingTrueUri": "sha1://07f578e5f2ae36565718ef90105ac079d1941d62/009_synth.firings_true.json"
                },
                {
                    "name": "010_synth",
                    "studyName": "synth_magland_noise10_K10_C4",
                    "studySetName": "SYNTH_MAGLAND",
                    "sampleRateHz": 30000.0,
                    "numChannels": 4,
                    "durationSec": 600.0,
                    "numTrueUnits": 10,
                    "spikeSign": -1,
                    "recordingUri": "sha1://c004e45240fc8b522d2f286ad7c0123e98c9ddc9/010_synth.json",
                    "sortingTrueUri": "sha1://e49db7ba4a161e9e8cd1761aa286591fb79ecde8/010_synth.firings_true.json"
                }
            ],
            "self_reference": "sha1://e9bd3826b91ffb7415afd694554a8ab6530092e9/synth_magland_noise10_K10_C4.json"
        },
        {
            "name": "synth_magland_noise10_K10_C8",
            "studySetName": "SYNTH_MAGLAND",
            "recordings": [
                {
                    "name": "001_synth",
                    "studyName": "synth_magland_noise10_K10_C8",
                    "studySetName": "SYNTH_MAGLAND",
                    "sampleRateHz": 30000.0,
                    "numChannels": 8,
                    "durationSec": 600.0,
                    "numTrueUnits": 10,
                    "spikeSign": -1,
                    "recordingUri": "sha1://3fba3afd6959ae625115d8318f20dd3dec2ca650/001_synth.json",
                    "sortingTrueUri": "sha1://a2576ca4ceb1d08c97b66ed33865dfc88ec9c9d2/001_synth.firings_true.json"
                },
                {
                    "name": "002_synth",
                    "studyName": "synth_magland_noise10_K10_C8",
                    "studySetName": "SYNTH_MAGLAND",
                    "sampleRateHz": 30000.0,
                    "numChannels": 8,
                    "durationSec": 600.0,
                    "numTrueUnits": 10,
                    "spikeSign": -1,
                    "recordingUri": "sha1://07bc04ab9e64a4a4d15fd7da8855821986a1104a/002_synth.json",
                    "sortingTrueUri": "sha1://a5a15488fe99602252b5f304b2a58c2d5c4d87e4/002_synth.firings_true.json"
                },
                {
                    "name": "003_synth",
                    "studyName": "synth_magland_noise10_K10_C8",
                    "studySetName": "SYNTH_MAGLAND",
                    "sampleRateHz": 30000.0,
                    "numChannels": 8,
                    "durationSec": 600.0,
                    "numTrueUnits": 10,
                    "spikeSign": -1,
                    "recordingUri": "sha1://3ddcb59933a950bd22ec13107cc76640eafc8c60/003_synth.json",
                    "sortingTrueUri": "sha1://14875461dd6fd6207b438add181be25e0fc27090/003_synth.firings_true.json"
                },
                {
                    "name": "004_synth",
                    "studyName": "synth_magland_noise10_K10_C8",
                    "studySetName": "SYNTH_MAGLAND",
                    "sampleRateHz": 30000.0,
                    "numChannels": 8,
                    "durationSec": 600.0,
                    "numTrueUnits": 10,
                    "spikeSign": -1,
                    "recordingUri": "sha1://500f93a28bfcdf8653031432ca334c5e9a8bfb9b/004_synth.json",
                    "sortingTrueUri": "sha1://78156d77702b60d8b180b6b9dcf51c667df08c11/004_synth.firings_true.json"
                },
                {
                    "name": "005_synth",
                    "studyName": "synth_magland_noise10_K10_C8",
                    "studySetName": "SYNTH_MAGLAND",
                    "sampleRateHz": 30000.0,
                    "numChannels": 8,
                    "durationSec": 600.0,
                    "numTrueUnits": 10,
                    "spikeSign": -1,
                    "recordingUri": "sha1://bab2d3105edbb84eeb22f91e0beb657b7e7e72e2/005_synth.json",
                    "sortingTrueUri": "sha1://1e2eb856ae92f56dbe27df506efd17c2f32d7e14/005_synth.firings_true.json"
                },
                {
                    "name": "006_synth",
                    "studyName": "synth_magland_noise10_K10_C8",
                    "studySetName": "SYNTH_MAGLAND",
                    "sampleRateHz": 30000.0,
                    "numChannels": 8,
                    "durationSec": 600.0,
                    "numTrueUnits": 10,
                    "spikeSign": -1,
                    "recordingUri": "sha1://09af41eeb87272e2d6ec3f2d92f01dbd0a504eb0/006_synth.json",
                    "sortingTrueUri": "sha1://fa474bd6d82de3969b9ab39cd364d6672fc4b97d/006_synth.firings_true.json"
                },
                {
                    "name": "007_synth",
                    "studyName": "synth_magland_noise10_K10_C8",
                    "studySetName": "SYNTH_MAGLAND",
                    "sampleRateHz": 30000.0,
                    "numChannels": 8,
                    "durationSec": 600.0,
                    "numTrueUnits": 10,
                    "spikeSign": -1,
                    "recordingUri": "sha1://77597d3d5b5d45638e2e825b97111746d3ce8f63/007_synth.json",
                    "sortingTrueUri": "sha1://9bb7993950cc3a3874f785be835264f8545e2735/007_synth.firings_true.json"
                },
                {
                    "name": "008_synth",
                    "studyName": "synth_magland_noise10_K10_C8",
                    "studySetName": "SYNTH_MAGLAND",
                    "sampleRateHz": 30000.0,
                    "numChannels": 8,
                    "durationSec": 600.0,
                    "numTrueUnits": 10,
                    "spikeSign": -1,
                    "recordingUri": "sha1://8f030449e125e8d9a6958da70b42a47bd4e27b65/008_synth.json",
                    "sortingTrueUri": "sha1://993b6617abfaada141236229a73d6750d10c0d58/008_synth.firings_true.json"
                },
                {
                    "name": "009_synth",
                    "studyName": "synth_magland_noise10_K10_C8",
                    "studySetName": "SYNTH_MAGLAND",
                    "sampleRateHz": 30000.0,
                    "numChannels": 8,
                    "durationSec": 600.0,
                    "numTrueUnits": 10,
                    "spikeSign": -1,
                    "recordingUri": "sha1://d283b69abbde174b3fbbac681f223e6d799e2646/009_synth.json",
                    "sortingTrueUri": "sha1://79764625bf6be31496fd5ff356feb60cf9689586/009_synth.firings_true.json"
                },
                {
                    "name": "010_synth",
                    "studyName": "synth_magland_noise10_K10_C8",
                    "studySetName": "SYNTH_MAGLAND",
                    "sampleRateHz": 30000.0,
                    "numChannels": 8,
                    "durationSec": 600.0,
                    "numTrueUnits": 10,
                    "spikeSign": -1,
                    "recordingUri": "sha1://0d52776b2af304244292183f9333a93312d9c2b5/010_synth.json",
                    "sortingTrueUri": "sha1://7fad2b0920e303b8692b3ee93abb2011e42e0639/010_synth.firings_true.json"
                }
            ],
            "self_reference": "sha1://c25563a7edb161433736ecd66691d7028b03d2ea/synth_magland_noise10_K10_C8.json"
        },
        {
            "name": "synth_magland_noise20_K10_C4",
            "studySetName": "SYNTH_MAGLAND",
            "recordings": [
                {
                    "name": "001_synth",
                    "studyName": "synth_magland_noise20_K10_C4",
                    "studySetName": "SYNTH_MAGLAND",
                    "sampleRateHz": 30000.0,
                    "numChannels": 4,
                    "durationSec": 600.0,
                    "numTrueUnits": 10,
                    "spikeSign": -1,
                    "recordingUri": "sha1://ce2349427e6cabae94fbb44ceac966799dc2d921/001_synth.json",
                    "sortingTrueUri": "sha1://8a316f384544ffd3694faa9e5710ee96a70b4b10/001_synth.firings_true.json"
                },
                {
                    "name": "002_synth",
                    "studyName": "synth_magland_noise20_K10_C4",
                    "studySetName": "SYNTH_MAGLAND",
                    "sampleRateHz": 30000.0,
                    "numChannels": 4,
                    "durationSec": 600.0,
                    "numTrueUnits": 10,
                    "spikeSign": -1,
                    "recordingUri": "sha1://37f48aeff7c7ecd68c09a430220247c215c8a228/002_synth.json",
                    "sortingTrueUri": "sha1://0c5762146dbdb123db56777e0d40f597ac78a15e/002_synth.firings_true.json"
                },
                {
                    "name": "003_synth",
                    "studyName": "synth_magland_noise20_K10_C4",
                    "studySetName": "SYNTH_MAGLAND",
                    "sampleRateHz": 30000.0,
                    "numChannels": 4,
                    "durationSec": 600.0,
                    "numTrueUnits": 10,
                    "spikeSign": -1,
                    "recordingUri": "sha1://bc400b78cd8d691aefb3477d12ca940801ec9362/003_synth.json",
                    "sortingTrueUri": "sha1://e7061729eee53784aaa1c9af36e3627062a250ba/003_synth.firings_true.json"
                },
                {
                    "name": "004_synth",
                    "studyName": "synth_magland_noise20_K10_C4",
                    "studySetName": "SYNTH_MAGLAND",
                    "sampleRateHz": 30000.0,
                    "numChannels": 4,
                    "durationSec": 600.0,
                    "numTrueUnits": 10,
                    "spikeSign": -1,
                    "recordingUri": "sha1://5c79fc399c86bf4d181ead564fc61e6b6ba22f7e/004_synth.json",
                    "sortingTrueUri": "sha1://512d076f2595fe569c92ce7170d19b57537ab2e9/004_synth.firings_true.json"
                },
                {
                    "name": "005_synth",
                    "studyName": "synth_magland_noise20_K10_C4",
                    "studySetName": "SYNTH_MAGLAND",
                    "sampleRateHz": 30000.0,
                    "numChannels": 4,
                    "durationSec": 600.0,
                    "numTrueUnits": 10,
                    "spikeSign": -1,
                    "recordingUri": "sha1://e9ad2da5efeb6d15b186c562058fdc8b85458f1d/005_synth.json",
                    "sortingTrueUri": "sha1://b4c03046d218f723de2c5e8b55dc1ba5e4d2f704/005_synth.firings_true.json"
                },
                {
                    "name": "006_synth",
                    "studyName": "synth_magland_noise20_K10_C4",
                    "studySetName": "SYNTH_MAGLAND",
                    "sampleRateHz": 30000.0,
                    "numChannels": 4,
                    "durationSec": 600.0,
                    "numTrueUnits": 10,
                    "spikeSign": -1,
                    "recordingUri": "sha1://1e80533e69b7c0f6b89366141fc1823b3f99f2ad/006_synth.json",
                    "sortingTrueUri": "sha1://688530c4bbc2e89fc54c63378be7930fcd33d438/006_synth.firings_true.json"
                },
                {
                    "name": "007_synth",
                    "studyName": "synth_magland_noise20_K10_C4",
                    "studySetName": "SYNTH_MAGLAND",
                    "sampleRateHz": 30000.0,
                    "numChannels": 4,
                    "durationSec": 600.0,
                    "numTrueUnits": 10,
                    "spikeSign": -1,
                    "recordingUri": "sha1://d79381ab3bd23a64a71a1fba94189631c9e2bafa/007_synth.json",
                    "sortingTrueUri": "sha1://9e6476ee0bbad6171dc39035e000c8b861b65e6c/007_synth.firings_true.json"
                },
                {
                    "name": "008_synth",
                    "studyName": "synth_magland_noise20_K10_C4",
                    "studySetName": "SYNTH_MAGLAND",
                    "sampleRateHz": 30000.0,
                    "numChannels": 4,
                    "durationSec": 600.0,
                    "numTrueUnits": 10,
                    "spikeSign": -1,
                    "recordingUri": "sha1://71d5680a2dc0be313d123c2ee07ca240b4d13ff1/008_synth.json",
                    "sortingTrueUri": "sha1://89bdd1f8051dba23cada3667e5ba6251da76379c/008_synth.firings_true.json"
                },
                {
                    "name": "009_synth",
                    "studyName": "synth_magland_noise20_K10_C4",
                    "studySetName": "SYNTH_MAGLAND",
                    "sampleRateHz": 30000.0,
                    "numChannels": 4,
                    "durationSec": 600.0,
                    "numTrueUnits": 10,
                    "spikeSign": -1,
                    "recordingUri": "sha1://7ba7317837d5d9f2cada88ba79accf4182222997/009_synth.json",
                    "sortingTrueUri": "sha1://5a302c6653577f87a9964c6ed4012805ac837d16/009_synth.firings_true.json"
                },
                {
                    "name": "010_synth",
                    "studyName": "synth_magland_noise20_K10_C4",
                    "studySetName": "SYNTH_MAGLAND",
                    "sampleRateHz": 30000.0,
                    "numChannels": 4,
                    "durationSec": 600.0,
                    "numTrueUnits": 10,
                    "spikeSign": -1,
                    "recordingUri": "sha1://4331c59865a7bc44f7d334d648ef89ea968df771/010_synth.json",
                    "sortingTrueUri": "sha1://6ec52c9c95412f1fadae227ca56f00c9f4d8c0ed/010_synth.firings_true.json"
                }
            ],
            "self_reference": "sha1://59510c07aad857c2a01cc9443174e4dbbb1dbf5d/synth_magland_noise20_K10_C4.json"
        },
        {
            "name": "synth_magland_noise20_K20_C4",
            "studySetName": "SYNTH_MAGLAND",
            "recordings": [
                {
                    "name": "001_synth",
                    "studyName": "synth_magland_noise20_K20_C4",
                    "studySetName": "SYNTH_MAGLAND",
                    "sampleRateHz": 30000.0,
                    "numChannels": 4,
                    "durationSec": 600.0,
                    "numTrueUnits": 20,
                    "spikeSign": -1,
                    "recordingUri": "sha1://3073756190420f8afd78daac81152cc8f39dca65/001_synth.json",
                    "sortingTrueUri": "sha1://769b1432424729cc6f88624008ea8bcd90466003/001_synth.firings_true.json"
                },
                {
                    "name": "002_synth",
                    "studyName": "synth_magland_noise20_K20_C4",
                    "studySetName": "SYNTH_MAGLAND",
                    "sampleRateHz": 30000.0,
                    "numChannels": 4,
                    "durationSec": 600.0,
                    "numTrueUnits": 20,
                    "spikeSign": -1,
                    "recordingUri": "sha1://613434e10cda5485c873c0011b5bc6e5092507a9/002_synth.json",
                    "sortingTrueUri": "sha1://6a1e4e6697b3744613881033e6c4ee89ffa54418/002_synth.firings_true.json"
                },
                {
                    "name": "003_synth",
                    "studyName": "synth_magland_noise20_K20_C4",
                    "studySetName": "SYNTH_MAGLAND",
                    "sampleRateHz": 30000.0,
                    "numChannels": 4,
                    "durationSec": 600.0,
                    "numTrueUnits": 20,
                    "spikeSign": -1,
                    "recordingUri": "sha1://ee38f3027c8f57a304950a9731e3c89a740bcb95/003_synth.json",
                    "sortingTrueUri": "sha1://cfd8ceaa64e96c9fad285d90cca8a9e401437add/003_synth.firings_true.json"
                },
                {
                    "name": "004_synth",
                    "studyName": "synth_magland_noise20_K20_C4",
                    "studySetName": "SYNTH_MAGLAND",
                    "sampleRateHz": 30000.0,
                    "numChannels": 4,
                    "durationSec": 600.0,
                    "numTrueUnits": 20,
                    "spikeSign": -1,
                    "recordingUri": "sha1://94e53bfde7fa02604086ec1543db9f9ec4a75562/004_synth.json",
                    "sortingTrueUri": "sha1://112a961d49f9d1e62e188892dd4ae8617db6daa7/004_synth.firings_true.json"
                },
                {
                    "name": "005_synth",
                    "studyName": "synth_magland_noise20_K20_C4",
                    "studySetName": "SYNTH_MAGLAND",
                    "sampleRateHz": 30000.0,
                    "numChannels": 4,
                    "durationSec": 600.0,
                    "numTrueUnits": 20,
                    "spikeSign": -1,
                    "recordingUri": "sha1://41f955029c50b4102b1a7dfdcf4ee6090abb6855/005_synth.json",
                    "sortingTrueUri": "sha1://c49c4a6978339129d156e5aa909d72b739d44a1f/005_synth.firings_true.json"
                },
                {
                    "name": "006_synth",
                    "studyName": "synth_magland_noise20_K20_C4",
                    "studySetName": "SYNTH_MAGLAND",
                    "sampleRateHz": 30000.0,
                    "numChannels": 4,
                    "durationSec": 600.0,
                    "numTrueUnits": 20,
                    "spikeSign": -1,
                    "recordingUri": "sha1://d7b04b8a2c76045daa9a0827977941633ed9016e/006_synth.json",
                    "sortingTrueUri": "sha1://e48f4654e24548a77b5c04485dd92b64338a9a4c/006_synth.firings_true.json"
                },
                {
                    "name": "007_synth",
                    "studyName": "synth_magland_noise20_K20_C4",
                    "studySetName": "SYNTH_MAGLAND",
                    "sampleRateHz": 30000.0,
                    "numChannels": 4,
                    "durationSec": 600.0,
                    "numTrueUnits": 20,
                    "spikeSign": -1,
                    "recordingUri": "sha1://d1b5c41561bc192c44925d9396f5cc5847e11de5/007_synth.json",
                    "sortingTrueUri": "sha1://3fa3b0def1c25c1d8536b187adea5a8b96256d14/007_synth.firings_true.json"
                },
                {
                    "name": "008_synth",
                    "studyName": "synth_magland_noise20_K20_C4",
                    "studySetName": "SYNTH_MAGLAND",
                    "sampleRateHz": 30000.0,
                    "numChannels": 4,
                    "durationSec": 600.0,
                    "numTrueUnits": 20,
                    "spikeSign": -1,
                    "recordingUri": "sha1://4ceb5a063a01dca6aa37a19240aa3de768ab80b6/008_synth.json",
                    "sortingTrueUri": "sha1://c7bab406fdcc156354202089247f7934f62fc3cf/008_synth.firings_true.json"
                },
                {
                    "name": "009_synth",
                    "studyName": "synth_magland_noise20_K20_C4",
                    "studySetName": "SYNTH_MAGLAND",
                    "sampleRateHz": 30000.0,
                    "numChannels": 4,
                    "durationSec": 600.0,
                    "numTrueUnits": 20,
                    "spikeSign": -1,
                    "recordingUri": "sha1://1a4258020628678041e1bb0f5eb35ce728a0ab3b/009_synth.json",
                    "sortingTrueUri": "sha1://907f792761ff5013a6b39222b96837a6715dfe88/009_synth.firings_true.json"
                },
                {
                    "name": "010_synth",
                    "studyName": "synth_magland_noise20_K20_C4",
                    "studySetName": "SYNTH_MAGLAND",
                    "sampleRateHz": 30000.0,
                    "numChannels": 4,
                    "durationSec": 600.0,
                    "numTrueUnits": 20,
                    "spikeSign": -1,
                    "recordingUri": "sha1://acb312ebb134b91fe110fa010151e7bfac57f6cc/010_synth.json",
                    "sortingTrueUri": "sha1://1dd4de8ff6f853e9c0e4c72b6187c453966ca98c/010_synth.firings_true.json"
                }
            ],
            "self_reference": "sha1://a3ca7c9e823019288a5ab851542f6f3effb3a2d6/synth_magland_noise20_K20_C4.json"
        },
        {
            "name": "synth_magland_noise20_K10_C8",
            "studySetName": "SYNTH_MAGLAND",
            "recordings": [
                {
                    "name": "001_synth",
                    "studyName": "synth_magland_noise20_K10_C8",
                    "studySetName": "SYNTH_MAGLAND",
                    "sampleRateHz": 30000.0,
                    "numChannels": 8,
                    "durationSec": 600.0,
                    "numTrueUnits": 10,
                    "spikeSign": -1,
                    "recordingUri": "sha1://38bc18907f3509d714194492d5239ddf896332e5/001_synth.json",
                    "sortingTrueUri": "sha1://f4719e6638f73f0a2218afcbd17154f1e9fc0c28/001_synth.firings_true.json"
                },
                {
                    "name": "002_synth",
                    "studyName": "synth_magland_noise20_K10_C8",
                    "studySetName": "SYNTH_MAGLAND",
                    "sampleRateHz": 30000.0,
                    "numChannels": 8,
                    "durationSec": 600.0,
                    "numTrueUnits": 10,
                    "spikeSign": -1,
                    "recordingUri": "sha1://a8134acd03b420ec02fea28c9933ce57f35710de/002_synth.json",
                    "sortingTrueUri": "sha1://78590083f7ba7b67ec8363bc4454b415cc1bff12/002_synth.firings_true.json"
                },
                {
                    "name": "003_synth",
                    "studyName": "synth_magland_noise20_K10_C8",
                    "studySetName": "SYNTH_MAGLAND",
                    "sampleRateHz": 30000.0,
                    "numChannels": 8,
                    "durationSec": 600.0,
                    "numTrueUnits": 10,
                    "spikeSign": -1,
                    "recordingUri": "sha1://bca42dbb011931f7492a12944704c45860dcad04/003_synth.json",
                    "sortingTrueUri": "sha1://44ff519c98fd0ddec268bc9e37b74d6b170c8e24/003_synth.firings_true.json"
                },
                {
                    "name": "004_synth",
                    "studyName": "synth_magland_noise20_K10_C8",
                    "studySetName": "SYNTH_MAGLAND",
                    "sampleRateHz": 30000.0,
                    "numChannels": 8,
                    "durationSec": 600.0,
                    "numTrueUnits": 10,
                    "spikeSign": -1,
                    "recordingUri": "sha1://4b89bfe23152f766e3a3f1284218047a2d6b44c8/004_synth.json",
                    "sortingTrueUri": "sha1://3dfcc65dfaeb05864af975bf013f0c2299fa6145/004_synth.firings_true.json"
                },
                {
                    "name": "005_synth",
                    "studyName": "synth_magland_noise20_K10_C8",
                    "studySetName": "SYNTH_MAGLAND",
                    "sampleRateHz": 30000.0,
                    "numChannels": 8,
                    "durationSec": 600.0,
                    "numTrueUnits": 10,
                    "spikeSign": -1,
                    "recordingUri": "sha1://916d5833571813bf424e2603131168a58bccf8a1/005_synth.json",
                    "sortingTrueUri": "sha1://e326179dc1d61b929fb319c2fdf2c0b21cf00ec6/005_synth.firings_true.json"
                },
                {
                    "name": "006_synth",
                    "studyName": "synth_magland_noise20_K10_C8",
                    "studySetName": "SYNTH_MAGLAND",
                    "sampleRateHz": 30000.0,
                    "numChannels": 8,
                    "durationSec": 600.0,
                    "numTrueUnits": 10,
                    "spikeSign": -1,
                    "recordingUri": "sha1://137270f3be667867011ed4da41c77545443de066/006_synth.json",
                    "sortingTrueUri": "sha1://07b927a8e1c1ada36fbad0951938ee7ad44003e4/006_synth.firings_true.json"
                },
                {
                    "name": "007_synth",
                    "studyName": "synth_magland_noise20_K10_C8",
                    "studySetName": "SYNTH_MAGLAND",
                    "sampleRateHz": 30000.0,
                    "numChannels": 8,
                    "durationSec": 600.0,
                    "numTrueUnits": 10,
                    "spikeSign": -1,
                    "recordingUri": "sha1://5557cc2b2a5ae7a09c9a481ab9bee3819257c3e1/007_synth.json",
                    "sortingTrueUri": "sha1://3e06087d5d9fa4455424bd1c108470141567b005/007_synth.firings_true.json"
                },
                {
                    "name": "008_synth",
                    "studyName": "synth_magland_noise20_K10_C8",
                    "studySetName": "SYNTH_MAGLAND",
                    "sampleRateHz": 30000.0,
                    "numChannels": 8,
                    "durationSec": 600.0,
                    "numTrueUnits": 10,
                    "spikeSign": -1,
                    "recordingUri": "sha1://04aa3aeebf14bbad4b584527c88f578e6c6413e8/008_synth.json",
                    "sortingTrueUri": "sha1://535858c84c09a1f63e1a41c1957ba6340b14d986/008_synth.firings_true.json"
                },
                {
                    "name": "009_synth",
                    "studyName": "synth_magland_noise20_K10_C8",
                    "studySetName": "SYNTH_MAGLAND",
                    "sampleRateHz": 30000.0,
                    "numChannels": 8,
                    "durationSec": 600.0,
                    "numTrueUnits": 10,
                    "spikeSign": -1,
                    "recordingUri": "sha1://434d55ab5b124d2bfc427509ac4113c80fb13dce/009_synth.json",
                    "sortingTrueUri": "sha1://e91b4c5b1975039e54377bd7b7687fac95d7fcec/009_synth.firings_true.json"
                },
                {
                    "name": "010_synth",
                    "studyName": "synth_magland_noise20_K10_C8",
                    "studySetName": "SYNTH_MAGLAND",
                    "sampleRateHz": 30000.0,
                    "numChannels": 8,
                    "durationSec": 600.0,
                    "numTrueUnits": 10,
                    "spikeSign": -1,
                    "recordingUri": "sha1://7e4defce075a91951d5cdaa6ec8292fae4b4d900/010_synth.json",
                    "sortingTrueUri": "sha1://2c794a86ea56c9e02d8208d87a5870df49b485f6/010_synth.firings_true.json"
                }
            ],
            "self_reference": "sha1://86f8ba724f95dc49e58a4ace37440057bbd75464/synth_magland_noise20_K10_C8.json"
        },
        {
            "name": "synth_magland_noise10_K20_C8",
            "studySetName": "SYNTH_MAGLAND",
            "recordings": [
                {
                    "name": "001_synth",
                    "studyName": "synth_magland_noise10_K20_C8",
                    "studySetName": "SYNTH_MAGLAND",
                    "sampleRateHz": 30000.0,
                    "numChannels": 8,
                    "durationSec": 600.0,
                    "numTrueUnits": 20,
                    "spikeSign": -1,
                    "recordingUri": "sha1://8b8c4538a5e822e6f96fad5fb80b90cdc647232f/001_synth.json",
                    "sortingTrueUri": "sha1://328aca3d75b7c6f54188f007ca3bf47fa1bf1ee0/001_synth.firings_true.json"
                },
                {
                    "name": "002_synth",
                    "studyName": "synth_magland_noise10_K20_C8",
                    "studySetName": "SYNTH_MAGLAND",
                    "sampleRateHz": 30000.0,
                    "numChannels": 8,
                    "durationSec": 600.0,
                    "numTrueUnits": 20,
                    "spikeSign": -1,
                    "recordingUri": "sha1://1859f2fe6f9d66df46ad853ad0a18c36a19f0968/002_synth.json",
                    "sortingTrueUri": "sha1://c05bdf61d78c21e86b6880eb0fe70c430b1a6b7d/002_synth.firings_true.json"
                },
                {
                    "name": "003_synth",
                    "studyName": "synth_magland_noise10_K20_C8",
                    "studySetName": "SYNTH_MAGLAND",
                    "sampleRateHz": 30000.0,
                    "numChannels": 8,
                    "durationSec": 600.0,
                    "numTrueUnits": 20,
                    "spikeSign": -1,
                    "recordingUri": "sha1://ee54fbd30fcc264cee1c2bdea9be3674671484eb/003_synth.json",
                    "sortingTrueUri": "sha1://e5d59866778115c10fa5db0576030db0fd57cb45/003_synth.firings_true.json"
                },
                {
                    "name": "004_synth",
                    "studyName": "synth_magland_noise10_K20_C8",
                    "studySetName": "SYNTH_MAGLAND",
                    "sampleRateHz": 30000.0,
                    "numChannels": 8,
                    "durationSec": 600.0,
                    "numTrueUnits": 20,
                    "spikeSign": -1,
                    "recordingUri": "sha1://854c0a9237de9479f72de6b1a97c16aa498e7482/004_synth.json",
                    "sortingTrueUri": "sha1://58d53062fa4f1f71edbeb22b38e632ba45c62027/004_synth.firings_true.json"
                },
                {
                    "name": "005_synth",
                    "studyName": "synth_magland_noise10_K20_C8",
                    "studySetName": "SYNTH_MAGLAND",
                    "sampleRateHz": 30000.0,
                    "numChannels": 8,
                    "durationSec": 600.0,
                    "numTrueUnits": 20,
                    "spikeSign": -1,
                    "recordingUri": "sha1://cf53e11a0a04dede50527b93a4b99c67714f9534/005_synth.json",
                    "sortingTrueUri": "sha1://d3fa1d1308c95efa3b909daa991a424a546c20d9/005_synth.firings_true.json"
                },
                {
                    "name": "006_synth",
                    "studyName": "synth_magland_noise10_K20_C8",
                    "studySetName": "SYNTH_MAGLAND",
                    "sampleRateHz": 30000.0,
                    "numChannels": 8,
                    "durationSec": 600.0,
                    "numTrueUnits": 20,
                    "spikeSign": -1,
                    "recordingUri": "sha1://9ad68f25c074de1ecc4193ac1428b8da035653b5/006_synth.json",
                    "sortingTrueUri": "sha1://e8fc11888b8d01bd927de4c6e8e71ab755f7491c/006_synth.firings_true.json"
                },
                {
                    "name": "007_synth",
                    "studyName": "synth_magland_noise10_K20_C8",
                    "studySetName": "SYNTH_MAGLAND",
                    "sampleRateHz": 30000.0,
                    "numChannels": 8,
                    "durationSec": 600.0,
                    "numTrueUnits": 20,
                    "spikeSign": -1,
                    "recordingUri": "sha1://cef02b830d85accc18ccd8781a167fef208c1cfd/007_synth.json",
                    "sortingTrueUri": "sha1://43ab2f080c37423365e4b967d0a2599a26267fa8/007_synth.firings_true.json"
                },
                {
                    "name": "008_synth",
                    "studyName": "synth_magland_noise10_K20_C8",
                    "studySetName": "SYNTH_MAGLAND",
                    "sampleRateHz": 30000.0,
                    "numChannels": 8,
                    "durationSec": 600.0,
                    "numTrueUnits": 20,
                    "spikeSign": -1,
                    "recordingUri": "sha1://a7075b212e269af623f7cccac282dc0259f50806/008_synth.json",
                    "sortingTrueUri": "sha1://4a941077ee3fd4ffef1db00e4b94bdedb7093a1e/008_synth.firings_true.json"
                },
                {
                    "name": "009_synth",
                    "studyName": "synth_magland_noise10_K20_C8",
                    "studySetName": "SYNTH_MAGLAND",
                    "sampleRateHz": 30000.0,
                    "numChannels": 8,
                    "durationSec": 600.0,
                    "numTrueUnits": 20,
                    "spikeSign": -1,
                    "recordingUri": "sha1://8299520aca6aa318ec24ecc111e41a0317d503df/009_synth.json",
                    "sortingTrueUri": "sha1://36a5783003ab6572541f22c15eebbd125cc84a6f/009_synth.firings_true.json"
                },
                {
                    "name": "010_synth",
                    "studyName": "synth_magland_noise10_K20_C8",
                    "studySetName": "SYNTH_MAGLAND",
                    "sampleRateHz": 30000.0,
                    "numChannels": 8,
                    "durationSec": 600.0,
                    "numTrueUnits": 20,
                    "spikeSign": -1,
                    "recordingUri": "sha1://72c88a1bc273d088c07d73c7a216917b59dc81dd/010_synth.json",
                    "sortingTrueUri": "sha1://2b9bc0289d16ebc2333ee1e4eebbf4b0edf66a73/010_synth.firings_true.json"
                }
            ],
            "self_reference": "sha1://67efcb470be468ec05a3a361eefea9582c8eab59/synth_magland_noise10_K20_C8.json"
        },
        {
            "name": "synth_magland_noise10_K20_C4",
            "studySetName": "SYNTH_MAGLAND",
            "recordings": [
                {
                    "name": "001_synth",
                    "studyName": "synth_magland_noise10_K20_C4",
                    "studySetName": "SYNTH_MAGLAND",
                    "sampleRateHz": 30000.0,
                    "numChannels": 4,
                    "durationSec": 600.0,
                    "numTrueUnits": 20,
                    "spikeSign": -1,
                    "recordingUri": "sha1://2853a58339add5472297887bf6ae520bfd58320b/001_synth.json",
                    "sortingTrueUri": "sha1://d40d1a2ec6f6bd3a5fd199b0a520acec11bc86dd/001_synth.firings_true.json"
                },
                {
                    "name": "002_synth",
                    "studyName": "synth_magland_noise10_K20_C4",
                    "studySetName": "SYNTH_MAGLAND",
                    "sampleRateHz": 30000.0,
                    "numChannels": 4,
                    "durationSec": 600.0,
                    "numTrueUnits": 20,
                    "spikeSign": -1,
                    "recordingUri": "sha1://8d7c67ccc5c2de60dead3923ad446bddbdab63b5/002_synth.json",
                    "sortingTrueUri": "sha1://69c68778ddd76035c3f8540b71ab948821d392fe/002_synth.firings_true.json"
                },
                {
                    "name": "003_synth",
                    "studyName": "synth_magland_noise10_K20_C4",
                    "studySetName": "SYNTH_MAGLAND",
                    "sampleRateHz": 30000.0,
                    "numChannels": 4,
                    "durationSec": 600.0,
                    "numTrueUnits": 20,
                    "spikeSign": -1,
                    "recordingUri": "sha1://bb29455ece4016d28de01c4b6758c14e1b37f4e7/003_synth.json",
                    "sortingTrueUri": "sha1://d4f50dbe9d5847e03419b6ac5636e55ddeb45039/003_synth.firings_true.json"
                },
                {
                    "name": "004_synth",
                    "studyName": "synth_magland_noise10_K20_C4",
                    "studySetName": "SYNTH_MAGLAND",
                    "sampleRateHz": 30000.0,
                    "numChannels": 4,
                    "durationSec": 600.0,
                    "numTrueUnits": 20,
                    "spikeSign": -1,
                    "recordingUri": "sha1://1d2607bbf1a51abd9c88d9ef19461578e2e6a863/004_synth.json",
                    "sortingTrueUri": "sha1://771026ae1c8a32bb79dd55a082c3556032463fbc/004_synth.firings_true.json"
                },
                {
                    "name": "005_synth",
                    "studyName": "synth_magland_noise10_K20_C4",
                    "studySetName": "SYNTH_MAGLAND",
                    "sampleRateHz": 30000.0,
                    "numChannels": 4,
                    "durationSec": 600.0,
                    "numTrueUnits": 20,
                    "spikeSign": -1,
                    "recordingUri": "sha1://1543ea0210fcf062f4ff665baba1dcd1a862614c/005_synth.json",
                    "sortingTrueUri": "sha1://9eccb541cd888a2d09fec0496f83b5e273933f64/005_synth.firings_true.json"
                },
                {
                    "name": "006_synth",
                    "studyName": "synth_magland_noise10_K20_C4",
                    "studySetName": "SYNTH_MAGLAND",
                    "sampleRateHz": 30000.0,
                    "numChannels": 4,
                    "durationSec": 600.0,
                    "numTrueUnits": 20,
                    "spikeSign": -1,
                    "recordingUri": "sha1://14752b4fafce54a717089777f99166de70912675/006_synth.json",
                    "sortingTrueUri": "sha1://f4d4755b96005fb8557c510a0d35822cecb7accf/006_synth.firings_true.json"
                },
                {
                    "name": "007_synth",
                    "studyName": "synth_magland_noise10_K20_C4",
                    "studySetName": "SYNTH_MAGLAND",
                    "sampleRateHz": 30000.0,
                    "numChannels": 4,
                    "durationSec": 600.0,
                    "numTrueUnits": 20,
                    "spikeSign": -1,
                    "recordingUri": "sha1://e3115c1edd42b124fde5e06d97571df759580c33/007_synth.json",
                    "sortingTrueUri": "sha1://dc1f6391dba05f11a5e6f1e1858caef8ae05e791/007_synth.firings_true.json"
                },
                {
                    "name": "008_synth",
                    "studyName": "synth_magland_noise10_K20_C4",
                    "studySetName": "SYNTH_MAGLAND",
                    "sampleRateHz": 30000.0,
                    "numChannels": 4,
                    "durationSec": 600.0,
                    "numTrueUnits": 20,
                    "spikeSign": -1,
                    "recordingUri": "sha1://aa1d91bb943fb09d80f2f314974cf45a8f0bec1c/008_synth.json",
                    "sortingTrueUri": "sha1://e9e86929cdc7833c6a1abeddc33aabd10a19b272/008_synth.firings_true.json"
                },
                {
                    "name": "009_synth",
                    "studyName": "synth_magland_noise10_K20_C4",
                    "studySetName": "SYNTH_MAGLAND",
                    "sampleRateHz": 30000.0,
                    "numChannels": 4,
                    "durationSec": 600.0,
                    "numTrueUnits": 20,
                    "spikeSign": -1,
                    "recordingUri": "sha1://47f60fa8178010b26013d6eea818f2fcded4999c/009_synth.json",
                    "sortingTrueUri": "sha1://5661898e7958130e177917a597d64882fec95c1d/009_synth.firings_true.json"
                },
                {
                    "name": "010_synth",
                    "studyName": "synth_magland_noise10_K20_C4",
                    "studySetName": "SYNTH_MAGLAND",
                    "sampleRateHz": 30000.0,
                    "numChannels": 4,
                    "durationSec": 600.0,
                    "numTrueUnits": 20,
                    "spikeSign": -1,
                    "recordingUri": "sha1://324d3ecef458cfd1120cbb28f085cf569c5af69b/010_synth.json",
                    "sortingTrueUri": "sha1://44663bed1ea9e7e20d893f9ea466a10d8846711e/010_synth.firings_true.json"
                }
            ],
            "self_reference": "sha1://b15e4f576d8b21b811fa2f74552988244df07871/synth_magland_noise10_K20_C4.json"
        }
    ],
    "self_reference": "sha1://846fce190098949bbb3ca6d2ebe591fe56cc7d0b/SYNTH_MAGLAND.json"
}