{
    "raw": "sha1://ee6302695b067f5eebab2dcc2e777a9584b065dc/raw.mda?manifest=9bc02d02cbb5b00335cccc395ae73032fda9ceef",
    "params": {
        "spike_sign": -1,
        "samplerate": 30000
    },
    "geom": [
        [
            43.0,
            20.0
        ],
        [
            11.0,
            20.0
        ],
        [
            59.0,
            40.0
        ],
        [
            27.0,
            40.0
        ],
        [
            43.0,
            60.0
        ],
        [
            11.0,
            60.0
        ],
        [
            59.0,
            80.0
        ],
        [
            27.0,
            80.0
        ]
    ],
    "self_reference": "sha1://6279c4e040c1502727ee48664e7d7440f2ec1ee4/001_synth.json"
}